scale/__init__.py
scale/cli.py
scale/client.py
scale/receive_log.py
scale/utils.py
skt_scale-1.0.1.dist-info/LICENSE
skt_scale-1.0.1.dist-info/METADATA
skt_scale-1.0.1.dist-info/WHEEL
skt_scale-1.0.1.dist-info/entry_points.txt
skt_scale-1.0.1.dist-info/top_level.txt
skt_scale-1.0.1.dist-info/RECORD
