Metadata-Version: 2.1
Name: skt-scale
Version: 1.0.1
Summary: UNKNOWN
Home-page: UNKNOWN
License: UNKNOWN
Platform: UNKNOWN
Requires-Dist: fire
Requires-Dist: requests
Requires-Dist: redis
Requires-Dist: enum34 ; python_version<'3'
Provides-Extra: test
Requires-Dist: pylint ; extra == 'test'
Requires-Dist: pytest ; extra == 'test'
Requires-Dist: pytest-mock ; extra == 'test'
Requires-Dist: responses ; extra == 'test'
